[
  {
    "title": "Home",
    "url": "#top",
    "ariaCurrent": true,
    "addClass": "nav-link w-100 active"
  },
  {
    "title": "Shop By Part Type",
    "url": "#top",
    "sub": [
      {
        "title": "Belts",
        "url": "#top"
      },
      {
        "title": "Blades",
        "url": "#top"
      },
      {
        "title": "Spark Plugs",
        "url": "#top"
      },
      {
        "title": "Carburetors",
        "url": "#top"
      },
      {
        "title": "Cables",
        "url": "#top"
      },
      {
        "title": "Filters",
        "url": "#top"
      },
      {
        "title": "Spindles",
        "url": "#top"
      },
      {
        "title": "Engine Parts",
        "url": "#top"
      },
      {
        "title": "Tires and Wheels",
        "url": "#top"
      },
      {
        "title": "Pulleys",
        "url": "#top"
      },
      {
        "title": "Oil, Lubricants and Fuel Additives",
        "url": "#top"
      },
      {
        "title": "Tiller Tines",
        "url": "#top"
      },
      {
        "title": "Engine Starters",
        "url": "#top",
        "sub": [
          { "title": "Electric Starter Motors", "url": "#top" },
          { "title": "Recoil Starters and Pull Ropes", "url": "#top" }
        ]
      },
      {
        "title": "Engine Maintenance Kits",
        "url": "#top"
      },
      {
        "title": "Seats",
        "url": "#top"
      },
      {
        "title": "Batteries",
        "url": "#top"
      },
      {
        "title": "Mower Decks",
        "url": "#top"
      },
      {
        "title": "Mufflers",
        "url": "#top"
      },
      {
        "title": "Trimmer Line",
        "url": "#top"
      },
      {
        "title": "Shave Plates and Skid Shoes",
        "url": "#top"
      },
      {
        "title": "Spindles",
        "url": "#top"
      },
      {
        "title": "Hardware",
        "url": "#top"
      },
      {
        "title": "Blade Adapters",
        "url": "#top"
      },
      {
        "title": "Universal Parts",
        "url": "#top"
      }
    ]
  },
  {
    "title": "Shop By Machine Type",
    "url": "#top",
    "sub": [
      {
        "title": "Vestibulum Posuere",
        "url": "#top"
      },
      {
        "title": "Condimentum Fermentum",
        "url": "#top"
      },
      {
        "title": "Mauris Mattis",
        "url": "#top"
      },
      {
        "title": "Nam Sed",
        "url": "#top"
      },
      {
        "title": "Sed Vitae",
        "url": "#top"
      },
      {
        "title": "Cras Fermentum",
        "url": "#top"
      },
      {
        "title": "Mauris Placerat Erat",
        "url": "#top"
      },
      {
        "title": "Ullamcorper Pharetra Metus",
        "url": "#top"
      },
      {
        "title": "Venenatis Lacinia Lobortis",
        "url": "#top"
      }
    ]
  },
  {
    "title": "Engine Parts",
    "url": "#top",
    "sub": [
      {
        "title": "Vestibulum Posuere",
        "url": "#top"
      },
      {
        "title": "Condimentum Fermentum",
        "url": "#top"
      },
      {
        "title": "Mauris Mattis",
        "url": "#top"
      },
      {
        "title": "Nam Sed",
        "url": "#top"
      },
      {
        "title": "Sed Vitae",
        "url": "#top"
      },
      {
        "title": "Cras Fermentum",
        "url": "#top"
      },
      {
        "title": "Mauris Placerat Erat",
        "url": "#top"
      },
      {
        "title": "Ullamcorper Pharetra Metus",
        "url": "#top"
      },
      {
        "title": "Venenatis Lacinia Lobortis",
        "url": "#top"
      }
    ]
  },
  {
    "title": "Accessories and Attachments",
    "url": "#top"
  },
  {
    "title": "Equipment",
    "url": "#top"
  },
  {
    "title": "Shop by Parts Diagram",
    "url": "#top"
  }
]
